{
  "account": {
    "initial_balance": 1000.0,
    "current_balance": 999.0605477624001
  },
  "performance": {
    "total_trades": 20,
    "winning_trades": 9,
    "losing_trades": 11,
    "win_rate": 45.0,
    "profit_factor": 0.46,
    "cumulative_pnl": -0.94,
    "total_return_pct": -0.09,
    "avg_win": 0.43,
    "avg_loss": 0.77,
    "max_drawdown_pct": -0.35,
    "current_drawdown_pct": -0.2,
    "sharpe_ratio": -8.96,
    "max_consecutive_wins": 5,
    "max_consecutive_losses": 4
  },
  "monthly_returns": {
    "2026-03": -0.45
  },
  "prediction_accuracy": {
    "total": 54,
    "correct": 26,
    "accuracy": 0.48,
    "avg_confidence": 0.52,
    "by_direction": {
      "UP": {
        "total": 4,
        "correct": 1
      },
      "DOWN": {
        "total": 50,
        "correct": 25
      },
      "NEUTRAL": {
        "total": 0,
        "correct": 0
      }
    }
  },
  "equity_curve": [
    {
      "time": "2026-03-23T06:00:38.439065+00:00",
      "balance": 1000.0
    },
    {
      "time": "2026-03-23T08:00:12.644021+00:00",
      "balance": 998.6001408475543
    },
    {
      "time": "2026-03-23T12:00:11.680901+00:00",
      "balance": 995.7814782502738
    },
    {
      "time": "2026-03-23T16:00:07.260833+00:00",
      "balance": 995.6335177929752
    },
    {
      "time": "2026-03-24T00:00:10.823693+00:00",
      "balance": 995.6881324709333
    },
    {
      "time": "2026-03-24T04:00:16.710202+00:00",
      "balance": 995.3399437058888
    },
    {
      "time": "2026-03-24T16:00:17.220848+00:00",
      "balance": 1000.6014649489241
    },
    {
      "time": "2026-03-24T20:00:27.970292+00:00",
      "balance": 1001.0536159600862
    },
    {
      "time": "2026-03-25T00:00:21.015374+00:00",
      "balance": 999.302366299597
    },
    {
      "time": "2026-03-25T04:00:17.540728+00:00",
      "balance": 998.614239956905
    },
    {
      "time": "2026-03-25T08:00:15.522681+00:00",
      "balance": 998.2162268343966
    },
    {
      "time": "2026-03-25T12:00:20.038514+00:00",
      "balance": 997.5881523815847
    },
    {
      "time": "2026-03-25T16:00:19.660240+00:00",
      "balance": 998.3841025954864
    },
    {
      "time": "2026-03-25T20:00:31.967791+00:00",
      "balance": 998.2413911130907
    },
    {
      "time": "2026-03-26T00:00:18.614367+00:00",
      "balance": 997.5781934097525
    },
    {
      "time": "2026-03-26T04:00:15.965899+00:00",
      "balance": 997.7691845628027
    },
    {
      "time": "2026-03-26T08:00:21.414181+00:00",
      "balance": 998.252314756628
    },
    {
      "time": "2026-03-26T12:00:19.981936+00:00",
      "balance": 999.0211110524513
    },
    {
      "time": "2026-03-26T16:00:16.694695+00:00",
      "balance": 999.0742327335314
    },
    {
      "time": "2026-03-26T20:00:19.527157+00:00",
      "balance": 999.5535115089376
    },
    {
      "time": "2026-03-27T00:00:30.619966+00:00",
      "balance": 999.0605477624001
    }
  ]
}